package_Swing/.DS_Store
package_Swing/__init__.py
package_Swing/basicStaticstics.py
package_Swing/contactList.py
package_Swing/dialpad.py
package_Swing/temperatureSwitch.py
package_swing-0.0.1.dist-info/METADATA
package_swing-0.0.1.dist-info/WHEEL
package_swing-0.0.1.dist-info/RECORD
