Metadata-Version: 2.1
Name: package_Swing
Version: 0.0.1
Summary: Swing's python project package
Project-URL: Homepage, https://github.com/swingfu/SwingPython
Project-URL: Bug Tracker, https://github.com/swingfu/SwingPython/issues
Author-email: Swing <swingfsy@outlook.com>
Classifier: License :: OSI Approved :: MIT License
Classifier: Operating System :: OS Independent
Classifier: Programming Language :: Python :: 3
Requires-Python: >=3.7
